LICENCE.md
MANIFEST.in
README.md
setup.py
polysquare_cmake_linter.egg-info/PKG-INFO
polysquare_cmake_linter.egg-info/SOURCES.txt
polysquare_cmake_linter.egg-info/dependency_links.txt
polysquare_cmake_linter.egg-info/entry_points.txt
polysquare_cmake_linter.egg-info/requires.txt
polysquare_cmake_linter.egg-info/top_level.txt
polysquare_cmake_linter.egg-info/zip-safe
polysquarecmakelinter/__init__.py
polysquarecmakelinter/check_access.py
polysquarecmakelinter/check_correctness.py
polysquarecmakelinter/check_structure.py
polysquarecmakelinter/check_style.py
polysquarecmakelinter/check_unused.py
polysquarecmakelinter/find_all.py
polysquarecmakelinter/find_set_variables.py
polysquarecmakelinter/find_variables_in_scopes.py
polysquarecmakelinter/ignore.py
polysquarecmakelinter/linter.py
polysquarecmakelinter/types.py
polysquarecmakelinter/util.py
test/__init__.py
test/autoderef_list.py
test/test_acceptance.py
test/test_access_warnings.py
test/test_correctness_warnings.py
test/test_find_variable_scopes.py
test/test_structure_warnings.py
test/test_style_warnings.py
test/test_unused_warnings.py
test/test_warnings.py
test/warnings_test_common.py