Metadata-Version: 1.1
Name: polysquare-cmake-linter
Version: 0.0.16
Summary: Polysquare CMake Linter
Home-page: http://github.com/polysquare/polysquare-cmake-linter
Author: Sam Spilsbury
Author-email: smspillaz@gmail.com
License: MIT
Keywords: development linters
Platform: UNKNOWN
Classifier: Development Status :: 3 - Alpha
Classifier: Programming Language :: Python :: 2
Classifier: Programming Language :: Python :: 2.7
Classifier: Programming Language :: Python :: 3
Classifier: Programming Language :: Python :: 3.1
Classifier: Programming Language :: Python :: 3.2
Classifier: Programming Language :: Python :: 3.3
Classifier: Programming Language :: Python :: 3.4
Classifier: Intended Audience :: Developers
Classifier: Topic :: Software Development :: Build Tools
Classifier: License :: OSI Approved :: MIT License
